citest_poetry/main.py
citest_poetry-0.1.1.dist-info/METADATA
citest_poetry-0.1.1.dist-info/WHEEL
citest_poetry-0.1.1.dist-info/RECORD
