Metadata-Version: 2.1
Name: citest-poetry
Version: 0.1.1
Summary: 
Author: Max Mehl
Author-email: mail@mehl.mx
Requires-Python: >=3.10,<4.0
Classifier: Programming Language :: Python :: 3
Classifier: Programming Language :: Python :: 3.10
Classifier: Programming Language :: Python :: 3.11
Classifier: Programming Language :: Python :: 3.12
Requires-Dist: gitpython (==3.1.41)
